signed_id/__init__.py
signed_id/signed_id.py
signed_id/test_signed_id.py
signed_id-0.1.0.dist-info/WHEEL
signed_id-0.1.0.dist-info/METADATA
signed_id-0.1.0.dist-info/RECORD
