Metadata-Version: 2.3
Name: signed-id
Version: 0.1.0
Summary: Generate and verify unique, signed short codes.
Author: Joe Nudell
Author-email: Joe Nudell <jnudell@hks.harvard.edu>
License: MIT
Requires-Python: >=3.10, <4
